pydoge_mysql/__init__.py
pydoge_mysql/mysql_client.py
PyDoge_mysql-0.1.1.dist-info/LICENSE
PyDoge_mysql-0.1.1.dist-info/METADATA
PyDoge_mysql-0.1.1.dist-info/WHEEL
PyDoge_mysql-0.1.1.dist-info/top_level.txt
PyDoge_mysql-0.1.1.dist-info/RECORD
